nfcpy_id_reader/__init__.py
nfcpy_id_reader/__main__.py
nfcpy_id_reader-0.1.0.dist-info/DESCRIPTION.rst
nfcpy_id_reader-0.1.0.dist-info/METADATA
nfcpy_id_reader-0.1.0.dist-info/RECORD
nfcpy_id_reader-0.1.0.dist-info/WHEEL
nfcpy_id_reader-0.1.0.dist-info/metadata.json
nfcpy_id_reader-0.1.0.dist-info/top_level.txt
