Metadata-Version: 2.0
Name: nfcpy-id-reader
Version: 0.1.0
Summary: Read the ID of an NFC Tag with nfcpy
Home-page: https://github.com/mascii/nfcpy_id_reader
Author: Masaki Koyanagi
Author-email: mascii@gmail.com
License: EUPL 1.1
Keywords: nfc pasori
Platform: UNKNOWN
Classifier: Programming Language :: Python :: 2.7
Requires-Dist: nfcpy
